tad_libcint/__init__.py
tad_libcint/_version.py
tad_libcint/api.py
tad_libcint/libcgto.so
tad_libcint/libcint.so
tad_libcint/libcint.so.6
tad_libcint/libcint.so.6.1.1
tad_libcint/libcvhf.so
tad_libcint/libnp_helper.so
tad_libcint/py.typed
tad_libcint/basis/__init__.py
tad_libcint/basis/datastructures.py
tad_libcint/interface/__init__.py
tad_libcint/interface/intor.py
tad_libcint/interface/namemanager.py
tad_libcint/interface/utils.py
tad_libcint/interface/wrapper.py
tad_libcint/interface/integrals/__init__.py
tad_libcint/interface/integrals/int_2c1e.py
tad_libcint/interface/integrals/utils.py
tad_libcint/interface/symmetry/__init__.py
tad_libcint/interface/symmetry/base.py
tad_libcint/interface/symmetry/s1.py
tad_libcint/interface/symmetry/s4.py
tad_libcint/lazyloader/__init__.py
tad_libcint/lazyloader/module.py
tad_libcint/lazyloader/so.py
tad_libcint/typing/__init__.py
tad_libcint/typing/builtin.py
tad_libcint/typing/compat.py
tad_libcint/typing/pytorch.py
tad_libcint.libs/libgfortran-ab4d54c3.so.5.0.0
tad_libcint.libs/libgomp-4b89c059.so.1.0.0
tad_libcint.libs/libopenblasp-r0-2332a278.3.27.so
tad_libcint.libs/libquadmath-57fec4cb.so.0.0.0
tad_libcint-0.2.0.dist-info/METADATA
tad_libcint-0.2.0.dist-info/WHEEL
tad_libcint-0.2.0.dist-info/top_level.txt
tad_libcint-0.2.0.dist-info/RECORD
tad_libcint-0.2.0.dist-info/licenses/LICENSE
