Metadata-Version: 2.4
Name: tad_libcint
Version: 0.2.0
Summary: "Torch Autodiff Libcint Interface"
Home-page: https://github.com/tad-mctc/tad-libcint/
Author: "Marvin Friede"
Author-email: friede@thch.uni-bonn.de
License: Apache-2.0
Project-URL: Documentation, https://github.com/tad-mctc/tad-libcint
Project-URL: Tracker, https://github.com/tad-mctc/tad-libcint/issues
Project-URL: Source Code, https://github.com/tad-mctc/tad-libcint
Keywords: tight-binding,quantum-chemistry,integrals,library
Classifier: Development Status :: 3 - Alpha
Classifier: Intended Audience :: Science/Research
Classifier: Operating System :: POSIX :: Linux
Classifier: Programming Language :: Python :: 3
Classifier: Programming Language :: Python :: 3 :: Only
Classifier: Programming Language :: Python :: 3.8
Classifier: Programming Language :: Python :: 3.9
Classifier: Programming Language :: Python :: 3.10
Classifier: Programming Language :: Python :: 3.11
Classifier: Programming Language :: Python :: 3.12
Classifier: Programming Language :: Python :: Implementation :: CPython
Classifier: Topic :: Scientific/Engineering
Classifier: Topic :: Scientific/Engineering :: Chemistry
Classifier: Topic :: Scientific/Engineering :: Mathematics
Classifier: Topic :: Scientific/Engineering :: Physics
Classifier: Typing :: Typed
Requires-Python: <3.13,>=3.8
License-File: LICENSE
Requires-Dist: numpy<2
Requires-Dist: tad-mctc
Requires-Dist: torch<3,>=1.11
Provides-Extra: dev
Requires-Dist: black; extra == "dev"
Requires-Dist: covdefaults; extra == "dev"
Requires-Dist: mypy; extra == "dev"
Requires-Dist: pre-commit; extra == "dev"
Requires-Dist: pylint; extra == "dev"
Requires-Dist: pytest; extra == "dev"
Requires-Dist: pytest-cov; extra == "dev"
Requires-Dist: pytest-random-order; extra == "dev"
Requires-Dist: pytest-xdist; extra == "dev"
Requires-Dist: tox; extra == "dev"
Provides-Extra: tox
Requires-Dist: covdefaults; extra == "tox"
Requires-Dist: pytest; extra == "tox"
Requires-Dist: pytest-cov; extra == "tox"
Requires-Dist: pytest-random-order; extra == "tox"
Requires-Dist: pytest-xdist; extra == "tox"
Dynamic: license-file
